snare/__init__.py
snare/snare.py
snare/core/__init__.py
snare/core/generation.py
snare/core/generator.py
snare/core/operation.py
snare/examples/lenet5.py
snare/wrappers/__init__.py
snare/wrappers/custom_layers.py
snare/wrappers/group.py
snare/wrappers/model_splitter.py
snare/wrappers/model_wrapper.py
snare_ml-0.1.0.dist-info/METADATA
snare_ml-0.1.0.dist-info/WHEEL
snare_ml-0.1.0.dist-info/top_level.txt
snare_ml-0.1.0.dist-info/RECORD
