Metadata-Version: 2.1
Name: snare-ml
Version: 0.1.0
Summary: Scorebased Neural Architecture REduction
Home-page: https://github.com/dk56/snare
Author: Tobias Viehmann
Author-email: tobias.viehmann@mail.de
License: MIT
Platform: UNKNOWN
Classifier: License :: OSI Approved :: MIT License
Classifier: Development Status :: 4 - Beta
Classifier: Intended Audience :: Information Technology
Classifier: Intended Audience :: Science/Research
Classifier: Programming Language :: Python
Classifier: Programming Language :: Python :: 3.6
Requires-Python: >=3.6.0
Requires-Dist: numpy (>=1.16.0)
Requires-Dist: tensorflow-gpu (==1.14.0)
